alienpy/__init__.py
alienpy/alien.py
alienpy/async_tools.py
alienpy/connect_ssl.py
alienpy/data_structs.py
alienpy/global_vars.py
alienpy/setup_cwd.py
alienpy/setup_logging.py
alienpy/tools_history.py
alienpy/tools_nowb.py
alienpy/tools_shell.py
alienpy/tools_stackcmd.py
alienpy/version.py
alienpy/wb_api.py
alienpy/wb_async.py
alienpy/xrd_core.py
alienpy/xrd_tools.py
alienpy-1.6.9.data/scripts/alien_wbtime
alienpy-1.6.9.dist-info/licenses/LICENSE
alienpy-1.6.9.dist-info/METADATA
alienpy-1.6.9.dist-info/WHEEL
alienpy-1.6.9.dist-info/entry_points.txt
alienpy-1.6.9.dist-info/top_level.txt
alienpy-1.6.9.dist-info/RECORD
