Metadata-Version: 2.4
Name: alienpy
Version: 1.6.9
Summary: Websocket based cli interface for ALICE experiment GRID infrastructure
Home-page: https://gitlab.cern.ch/jalien/xjalienfs
Author: Adrian Sevcenco
Author-email: adrian.sevcenco@cern.ch
License: BSD-3-Clause
Project-URL: Dev git, https://github.com/adriansev/jalien_py
Project-URL: Issues, https://github.com/adriansev/jalien_py/issues
Project-URL: Changelog, https://github.com/adriansev/jalien_py/commits/master
Project-URL: Documentation, https://jalien.docs.cern.ch
Project-URL: CERN Mattermost/JAliEn, https://mattermost.web.cern.ch/alice/channels/jalien
Keywords: CERN ALICE JAliEn GRID
Classifier: Programming Language :: Python :: 3
Classifier: Operating System :: OS Independent
Requires-Python: >=3.9
License-File: LICENSE
Requires-Dist: async-stagger>=0.3.1
Requires-Dist: pyOpenSSL>=25.0.0
Requires-Dist: rich
Requires-Dist: requests
Requires-Dist: xmltodict
Requires-Dist: humanfriendly
Requires-Dist: websockets>=15.0.0
Requires-Dist: xrootd>=5.8.2
Dynamic: author
Dynamic: author-email
Dynamic: classifier
Dynamic: description
Dynamic: description-content-type
Dynamic: home-page
Dynamic: keywords
Dynamic: license
Dynamic: license-file
Dynamic: project-url
Dynamic: requires-dist
Dynamic: requires-python
Dynamic: summary
